rdflib/__init__.py
rdflib/_networking.py
rdflib/_type_checking.py
rdflib/collection.py
rdflib/compare.py
rdflib/compat.py
rdflib/container.py
rdflib/events.py
rdflib/exceptions.py
rdflib/extras/__init__.py
rdflib/extras/cmdlineutils.py
rdflib/extras/describer.py
rdflib/extras/external_graph_libs.py
rdflib/extras/infixowl.py
rdflib/extras/shacl.py
rdflib/graph.py
rdflib/namespace/_BRICK.py
rdflib/namespace/_CSVW.py
rdflib/namespace/_DC.py
rdflib/namespace/_DCAM.py
rdflib/namespace/_DCAT.py
rdflib/namespace/_DCMITYPE.py
rdflib/namespace/_DCTERMS.py
rdflib/namespace/_DOAP.py
rdflib/namespace/_FOAF.py
rdflib/namespace/_GEO.py
rdflib/namespace/_ODRL2.py
rdflib/namespace/_ORG.py
rdflib/namespace/_OWL.py
rdflib/namespace/_PROF.py
rdflib/namespace/_PROV.py
rdflib/namespace/_QB.py
rdflib/namespace/_RDF.py
rdflib/namespace/_RDFS.py
rdflib/namespace/_SDO.py
rdflib/namespace/_SH.py
rdflib/namespace/_SKOS.py
rdflib/namespace/_SOSA.py
rdflib/namespace/_SSN.py
rdflib/namespace/_TIME.py
rdflib/namespace/_VANN.py
rdflib/namespace/_VOID.py
rdflib/namespace/_WGS.py
rdflib/namespace/_XSD.py
rdflib/namespace/__init__.py
rdflib/parser.py
rdflib/paths.py
rdflib/plugin.py
rdflib/plugins/__init__.py
rdflib/plugins/parsers/RDFVOC.py
rdflib/plugins/parsers/__init__.py
rdflib/plugins/parsers/hext.py
rdflib/plugins/parsers/jsonld.py
rdflib/plugins/parsers/notation3.py
rdflib/plugins/parsers/nquads.py
rdflib/plugins/parsers/ntriples.py
rdflib/plugins/parsers/patch.py
rdflib/plugins/parsers/rdfxml.py
rdflib/plugins/parsers/trig.py
rdflib/plugins/parsers/trix.py
rdflib/plugins/serializers/__init__.py
rdflib/plugins/serializers/hext.py
rdflib/plugins/serializers/jsonld.py
rdflib/plugins/serializers/longturtle.py
rdflib/plugins/serializers/n3.py
rdflib/plugins/serializers/nquads.py
rdflib/plugins/serializers/nt.py
rdflib/plugins/serializers/patch.py
rdflib/plugins/serializers/rdfxml.py
rdflib/plugins/serializers/trig.py
rdflib/plugins/serializers/trix.py
rdflib/plugins/serializers/turtle.py
rdflib-7.2.0.dist-info/METADATA
rdflib-7.2.0.dist-info/WHEEL
rdflib-7.2.0.dist-info/entry_points.txt
rdflib-7.2.0.dist-info/licenses/LICENSE
rdflib-7.2.0.dist-info/RECORD
