Metadata-Version: 2.4
Name: rdflib
Version: 7.2.0
Summary: RDFLib is a Python library for working with RDF, a simple yet powerful language for representing information.
License: BSD-3-Clause
License-File: LICENSE
Author: Daniel 'eikeon' Krech
Author-email: eikeon@eikeon.com
Maintainer: RDFLib Team
Maintainer-email: rdflib-dev@googlegroups.com
Requires-Python: >=3.8.1,<4.0.0
Classifier: License :: OSI Approved :: BSD License
Classifier: Natural Language :: English
Classifier: Operating System :: OS Independent
Classifier: Programming Language :: Python
Classifier: Programming Language :: Python :: 3
Classifier: Programming Language :: Python :: 3.9
Classifier: Programming Language :: Python :: 3.10
Classifier: Programming Language :: Python :: 3.11
Classifier: Programming Language :: Python :: 3.12
Classifier: Programming Language :: Python :: 3.13
Classifier: Programming Language :: Python :: 3.14
Classifier: Programming Language :: Python :: 3.8
Classifier: Topic :: Software Development :: Libraries :: Python Modules
Provides-Extra: berkeleydb
Provides-Extra: html
Provides-Extra: lxml
Provides-Extra: networkx
Provides-Extra: orjson
Requires-Dist: berkeleydb (>=18.1.0,<19.0.0) ; extra == "berkeleydb"
Requires-Dist: html5rdf (>=1.2,<2) ; extra == "html"
Requires-Dist: isodate (>=0.7.2,<1.0.0) ; python_version < "3.11"
Requires-Dist: lxml (>=4.3,<6.0) ; extra == "lxml"
Requires-Dist: networkx (>=2,<4) ; extra == "networkx"
Requires-Dist: orjson (>=3.9.14,<4) ; extra == "orjson"
Requires-Dist: pyparsing (>=2.1.0,<4)
Project-URL: Documentation, https://rdflib.readthedocs.org/
Project-URL: Repository, https://github.com/RDFLib/rdflib
